manim_neural_network/__init__.py
manim_neural_network/neural_network.py
manim_neural_network-0.1.0.dist-info/LICENSE
manim_neural_network-0.1.0.dist-info/METADATA
manim_neural_network-0.1.0.dist-info/WHEEL
manim_neural_network-0.1.0.dist-info/top_level.txt
manim_neural_network-0.1.0.dist-info/RECORD
