Metadata-Version: 2.1
Name: manim-neural-network
Version: 0.1.0
Summary: A library for visualizing neural networks in Manim
Home-page: https://github.com/JPM2002/manim-neural-network
Author: Javier Pozo Miranda
Author-email: jdp5958@psu.edu
Classifier: Programming Language :: Python :: 3
Classifier: License :: OSI Approved :: MIT License
Classifier: Operating System :: OS Independent
Requires-Python: >=3.7
License-File: LICENSE
Requires-Dist: manim
